wagtailkatex/__init__.py
wagtailkatex/richtext.py
wagtailkatex/wagtail_hooks.py
wagtailkatex/static/.DS_Store
wagtailkatex/static/wagtailkatex/wagtailkatex.css
wagtailkatex/static/wagtailkatex/wagtailkatex.js
wagtailkatex/static/wagtailkatex/katex/README.md
wagtailkatex/static/wagtailkatex/katex/katex.min.css
wagtailkatex/static/wagtailkatex/katex/katex.min.js
wagtailkatex/static/wagtailkatex/katex/fonts/KaTeX_AMS-Regular.ttf
wagtailkatex/static/wagtailkatex/katex/fonts/KaTeX_AMS-Regular.woff
wagtailkatex/static/wagtailkatex/katex/fonts/KaTeX_AMS-Regular.woff2
wagtailkatex/static/wagtailkatex/katex/fonts/KaTeX_Caligraphic-Bold.ttf
wagtailkatex/static/wagtailkatex/katex/fonts/KaTeX_Caligraphic-Bold.woff
wagtailkatex/static/wagtailkatex/katex/fonts/KaTeX_Caligraphic-Bold.woff2
wagtailkatex/static/wagtailkatex/katex/fonts/KaTeX_Caligraphic-Regular.ttf
wagtailkatex/static/wagtailkatex/katex/fonts/KaTeX_Caligraphic-Regular.woff
wagtailkatex/static/wagtailkatex/katex/fonts/KaTeX_Caligraphic-Regular.woff2
wagtailkatex/static/wagtailkatex/katex/fonts/KaTeX_Fraktur-Bold.ttf
wagtailkatex/static/wagtailkatex/katex/fonts/KaTeX_Fraktur-Bold.woff
wagtailkatex/static/wagtailkatex/katex/fonts/KaTeX_Fraktur-Bold.woff2
wagtailkatex/static/wagtailkatex/katex/fonts/KaTeX_Fraktur-Regular.ttf
wagtailkatex/static/wagtailkatex/katex/fonts/KaTeX_Fraktur-Regular.woff
wagtailkatex/static/wagtailkatex/katex/fonts/KaTeX_Fraktur-Regular.woff2
wagtailkatex/static/wagtailkatex/katex/fonts/KaTeX_Main-Bold.ttf
wagtailkatex/static/wagtailkatex/katex/fonts/KaTeX_Main-Bold.woff
wagtailkatex/static/wagtailkatex/katex/fonts/KaTeX_Main-Bold.woff2
wagtailkatex/static/wagtailkatex/katex/fonts/KaTeX_Main-BoldItalic.ttf
wagtailkatex/static/wagtailkatex/katex/fonts/KaTeX_Main-BoldItalic.woff
wagtailkatex/static/wagtailkatex/katex/fonts/KaTeX_Main-BoldItalic.woff2
wagtailkatex/static/wagtailkatex/katex/fonts/KaTeX_Main-Italic.ttf
wagtailkatex/static/wagtailkatex/katex/fonts/KaTeX_Main-Italic.woff
wagtail_katex-0.0.6.dist-info/LICENSE
wagtail_katex-0.0.6.dist-info/METADATA
wagtail_katex-0.0.6.dist-info/WHEEL
wagtail_katex-0.0.6.dist-info/top_level.txt
wagtail_katex-0.0.6.dist-info/RECORD
