Metadata-Version: 2.1
Name: wagtail-katex
Version: 0.0.6
Summary: Math typesetting for Wagtail CMS powered by KaTeX
Author-email: ongchi <ongchi@users.noreply.github.com>
License: MIT
Project-URL: Homepage, https://github.com/ongchi/wagtail-katex
Project-URL: Bug Tracker, https://github.com/ongchi/wagtail-katex/issues
Classifier: Environment :: Web Environment
Classifier: Framework :: Django
Classifier: Framework :: Wagtail
Classifier: Framework :: Wagtail :: 3
Classifier: Framework :: Wagtail :: 4
Classifier: Framework :: Wagtail :: 5
Classifier: Intended Audience :: Developers
Classifier: License :: OSI Approved :: Apache Software License
Classifier: Operating System :: OS Independent
Classifier: Programming Language :: Python
Classifier: Programming Language :: Python :: 3
Classifier: Programming Language :: Python :: 3.10
Classifier: Programming Language :: Python :: 3.6
Classifier: Programming Language :: Python :: 3.7
Classifier: Programming Language :: Python :: 3.8
Classifier: Programming Language :: Python :: 3.9
Requires-Python: >=3.6
License-File: LICENSE
Requires-Dist: wagtail (>=3)
